{
  "version": "5.10.1",
  "flags": {},
  "shapes": [
    {
      "label": "motorbike",
      "points": [
        [
          347.0550842285156,
          164.0235595703125
        ]
      ],
      "group_id": null,
      "description": "333.02,153.81,361.09,174.23",
      "shape_type": "point",
      "flags": {}
    },
    {
      "label": "car",
      "points": [
        [
          55.923309326171875,
          116.88266372680664
        ]
      ],
      "group_id": null,
      "description": "32.33,106.79,79.52,126.98",
      "shape_type": "point",
      "flags": {}
    },
    {
      "label": "motorbike",
      "points": [
        [
          362.55943298339844,
          105.41107940673828
        ]
      ],
      "group_id": null,
      "description": "353.44,98.59,371.67,112.23",
      "shape_type": "point",
      "flags": {}
    }
  ],
  "imagePath": "20251118_174336_082.jpg",
  "imageData": null,
  "imageHeight": 294,
  "imageWidth": 518
}