{
  "version": "6.3.0",
  "flags": {},
  "shapes": [
    {
      "label": "motorbike",
      "points": [
        [
          278.19337463378906,
          117.93248748779297
        ]
      ],
      "group_id": null,
      "description": "268.04,110.38,288.35,125.48",
      "shape_type": "point",
      "flags": {},
      "mask": null
    },
    {
      "label": "car",
      "points": [
        [
          460.2105712890625,
          248.1113052368164
        ]
      ],
      "group_id": null,
      "description": "414.45,227.76,505.97,268.46",
      "shape_type": "point",
      "flags": {},
      "mask": null
    },
    {
      "label": "coach",
      "points": [
        [
          135.80412371134022,
          111.60481099656359
        ]
      ],
      "group_id": null,
      "description": "",
      "shape_type": "point",
      "flags": {},
      "mask": null
    },
    {
      "label": "car",
      "points": [
        [
          114.15463917525774,
          174.49140893470792
        ]
      ],
      "group_id": null,
      "description": "",
      "shape_type": "point",
      "flags": {},
      "mask": null
    }
  ],
  "imagePath": "20251116_150737_020.jpg",
  "imageData": null,
  "imageHeight": 294,
  "imageWidth": 518
}