{
  "version": "5.10.1",
  "flags": {},
  "shapes": [
    {
      "label": "motorbike",
      "points": [
        [
          242.86286163330078,
          102.71914672851562
        ]
      ],
      "group_id": null,
      "description": "233.71,95.88,252.01,109.56",
      "shape_type": "point",
      "flags": {}
    },
    {
      "label": "motorbike",
      "points": [
        [
          282.1644744873047,
          97.7174301147461
        ]
      ],
      "group_id": null,
      "description": "273.34,91.13,290.99,104.31",
      "shape_type": "point",
      "flags": {}
    }
  ],
  "imagePath": "20251118_173033_004.jpg",
  "imageData": null,
  "imageHeight": 294,
  "imageWidth": 518
}