{
  "version": "6.3.0",
  "flags": {},
  "shapes": [
    {
      "label": "motorbike",
      "points": [
        [
          422.1333770751953,
          169.4017105102539
        ]
      ],
      "group_id": null,
      "description": "407.51,159.00,436.76,179.81",
      "shape_type": "point",
      "flags": {},
      "mask": null
    },
    {
      "label": "car",
      "points": [
        [
          237.25359344482422,
          150.16094970703125
        ]
      ],
      "group_id": null,
      "description": "207.94,137.58,266.57,162.75",
      "shape_type": "point",
      "flags": {},
      "mask": null
    },
    {
      "label": "car",
      "points": [
        [
          273.23941802978516,
          206.11129760742188
        ]
      ],
      "group_id": null,
      "description": "234.88,189.29,311.60,222.94",
      "shape_type": "point",
      "flags": {},
      "mask": null
    },
    {
      "label": "car",
      "points": [
        [
          130.91986465454102,
          139.50562286376953
        ]
      ],
      "group_id": null,
      "description": "103.90,127.73,157.94,151.28",
      "shape_type": "point",
      "flags": {},
      "mask": null
    },
    {
      "label": "car",
      "points": [
        [
          211.8849334716797,
          126.36378479003906
        ]
      ],
      "group_id": null,
      "description": "187.54,115.86,236.23,136.87",
      "shape_type": "point",
      "flags": {},
      "mask": null
    },
    {
      "label": "motorbike",
      "points": [
        [
          259.6144485473633,
          133.4738540649414
        ]
      ],
      "group_id": null,
      "description": "247.93,125.07,271.30,141.87",
      "shape_type": "point",
      "flags": {},
      "mask": null
    },
    {
      "label": "car",
      "points": [
        [
          149.58467483520508,
          160.74506378173828
        ]
      ],
      "group_id": null,
      "description": "118.51,147.40,180.66,174.09",
      "shape_type": "point",
      "flags": {},
      "mask": null
    },
    {
      "label": "car",
      "points": [
        [
          203.5803451538086,
          144.24497985839844
        ]
      ],
      "group_id": null,
      "description": "175.79,132.44,231.37,156.05",
      "shape_type": "point",
      "flags": {},
      "mask": null
    },
    {
      "label": "motorbike",
      "points": [
        [
          126.1745719909668,
          107.03853988647461
        ]
      ],
      "group_id": null,
      "description": "117.04,100.30,135.31,113.77",
      "shape_type": "point",
      "flags": {},
      "mask": null
    },
    {
      "label": "car",
      "points": [
        [
          66.27716255187988,
          118.76833724975586
        ]
      ],
      "group_id": null,
      "description": "42.61,108.72,89.95,128.82",
      "shape_type": "point",
      "flags": {},
      "mask": null
    },
    {
      "label": "car",
      "points": [
        [
          249.64154815673828,
          118.74538040161133
        ]
      ],
      "group_id": null,
      "description": "226.23,108.94,273.05,128.55",
      "shape_type": "point",
      "flags": {},
      "mask": null
    },
    {
      "label": "car",
      "points": [
        [
          177.53729248046875,
          135.02400588989258
        ]
      ],
      "group_id": null,
      "description": "151.41,123.84,203.67,146.20",
      "shape_type": "point",
      "flags": {},
      "mask": null
    },
    {
      "label": "car",
      "points": [
        [
          268.12569427490234,
          178.61609649658203
        ]
      ],
      "group_id": null,
      "description": "233.78,163.88,302.48,193.35",
      "shape_type": "point",
      "flags": {},
      "mask": null
    },
    {
      "label": "motorbike",
      "points": [
        [
          266.04723358154297,
          145.64354705810547
        ]
      ],
      "group_id": null,
      "description": "253.51,136.53,278.58,154.76",
      "shape_type": "point",
      "flags": {},
      "mask": null
    },
    {
      "label": "motorbike",
      "points": [
        [
          193.01476287841797,
          127.32675552368164
        ]
      ],
      "group_id": null,
      "description": "182.21,119.49,203.81,135.17",
      "shape_type": "point",
      "flags": {},
      "mask": null
    },
    {
      "label": "motorbike",
      "points": [
        [
          229.06774139404297,
          123.82705307006836
        ]
      ],
      "group_id": null,
      "description": "218.47,116.14,239.67,131.52",
      "shape_type": "point",
      "flags": {},
      "mask": null
    },
    {
      "label": "car",
      "points": [
        [
          176.60943603515625,
          119.57684707641602
        ]
      ],
      "group_id": null,
      "description": "153.15,109.64,200.07,129.51",
      "shape_type": "point",
      "flags": {},
      "mask": null
    },
    {
      "label": "car",
      "points": [
        [
          203.7286834716797,
          108.00105667114258
        ]
      ],
      "group_id": null,
      "description": "182.29,98.88,225.17,117.12",
      "shape_type": "point",
      "flags": {},
      "mask": null
    },
    {
      "label": "motorbike",
      "points": [
        [
          234.82807159423828,
          116.56667709350586
        ]
      ],
      "group_id": null,
      "description": "224.86,109.26,244.80,123.88",
      "shape_type": "point",
      "flags": {},
      "mask": null
    },
    {
      "label": "car",
      "points": [
        [
          376.4157303370786,
          157.4868913857678
        ]
      ],
      "group_id": null,
      "description": "",
      "shape_type": "point",
      "flags": {},
      "mask": null
    },
    {
      "label": "car",
      "points": [
        [
          61.43445692883895,
          249.62172284644194
        ]
      ],
      "group_id": null,
      "description": "",
      "shape_type": "point",
      "flags": {},
      "mask": null
    }
  ],
  "imagePath": "20251118_170630_039.jpg",
  "imageData": null,
  "imageHeight": 294,
  "imageWidth": 518
}