{
  "version": "5.10.1",
  "flags": {},
  "shapes": [
    {
      "label": "motorbike",
      "points": [
        [
          228.10923767089844,
          145.12503051757812
        ]
      ],
      "group_id": null,
      "description": "215.76,136.22,240.46,154.03",
      "shape_type": "point",
      "flags": {}
    },
    {
      "label": "motorbike",
      "points": [
        [
          244.7484588623047,
          140.65542602539062
        ]
      ],
      "group_id": null,
      "description": "232.60,131.87,256.90,149.44",
      "shape_type": "point",
      "flags": {}
    },
    {
      "label": "motorbike",
      "points": [
        [
          253.69827270507812,
          181.87203216552734
        ]
      ],
      "group_id": null,
      "description": "238.19,170.72,269.20,193.02",
      "shape_type": "point",
      "flags": {}
    },
    {
      "label": "motorbike",
      "points": [
        [
          219.96580505371094,
          159.81070709228516
        ]
      ],
      "group_id": null,
      "description": "206.30,149.96,233.63,169.66",
      "shape_type": "point",
      "flags": {}
    },
    {
      "label": "motorbike",
      "points": [
        [
          188.7208251953125,
          128.62996673583984
        ]
      ],
      "group_id": null,
      "description": "177.88,120.79,199.56,136.47",
      "shape_type": "point",
      "flags": {}
    },
    {
      "label": "car",
      "points": [
        [
          165.5677032470703,
          117.40026092529297
        ]
      ],
      "group_id": null,
      "description": "142.85,107.67,188.29,127.13",
      "shape_type": "point",
      "flags": {}
    },
    {
      "label": "motorbike",
      "points": [
        [
          265.1808624267578,
          145.73848724365234
        ]
      ],
      "group_id": null,
      "description": "252.62,136.62,277.75,154.86",
      "shape_type": "point",
      "flags": {}
    },
    {
      "label": "coach",
      "points": [
        [
          229.30575561523438,
          112.5652084350586
        ]
      ],
      "group_id": null,
      "description": "193.83,101.64,264.78,123.49",
      "shape_type": "point",
      "flags": {}
    },
    {
      "label": "car",
      "points": [
        [
          169.10885620117188,
          149.08873748779297
        ]
      ],
      "group_id": null,
      "description": "140.44,136.44,197.77,161.74",
      "shape_type": "point",
      "flags": {}
    },
    {
      "label": "motorbike",
      "points": [
        [
          405.28826904296875,
          232.9583740234375
        ]
      ],
      "group_id": null,
      "description": "385.67,219.18,424.91,246.73",
      "shape_type": "point",
      "flags": {}
    },
    {
      "label": "car",
      "points": [
        [
          206.17088317871094,
          124.9235725402832
        ]
      ],
      "group_id": null,
      "description": "181.54,114.48,230.80,135.37",
      "shape_type": "point",
      "flags": {}
    },
    {
      "label": "motorbike",
      "points": [
        [
          203.61585998535156,
          177.31153869628906
        ]
      ],
      "group_id": null,
      "description": "188.53,166.57,218.70,188.05",
      "shape_type": "point",
      "flags": {}
    },
    {
      "label": "motorbike",
      "points": [
        [
          402.59230041503906,
          180.54214477539062
        ]
      ],
      "group_id": null,
      "description": "387.21,169.49,417.97,191.59",
      "shape_type": "point",
      "flags": {}
    },
    {
      "label": "motorbike",
      "points": [
        [
          217.36783599853516,
          115.75537109375
        ]
      ],
      "group_id": null,
      "description": "207.44,108.56,227.29,122.95",
      "shape_type": "point",
      "flags": {}
    },
    {
      "label": "car",
      "points": [
        [
          193.25332641601562,
          118.39581680297852
        ]
      ],
      "group_id": null,
      "description": "170.55,108.60,215.96,128.19",
      "shape_type": "point",
      "flags": {}
    },
    {
      "label": "car",
      "points": [
        [
          146.92046356201172,
          105.14369201660156
        ]
      ],
      "group_id": null,
      "description": "125.71,96.18,168.13,114.10",
      "shape_type": "point",
      "flags": {}
    },
    {
      "label": "motorbike",
      "points": [
        [
          38.78307056427002,
          124.01495742797852
        ]
      ],
      "group_id": null,
      "description": "28.24,116.26,49.32,131.77",
      "shape_type": "point",
      "flags": {}
    }
  ],
  "imagePath": "20251118_171258_077.jpg",
  "imageData": null,
  "imageHeight": 294,
  "imageWidth": 518
}