{
  "version": "5.10.1",
  "flags": {},
  "shapes": [
    {
      "label": "motorbike",
      "points": [
        [
          135.0158576965332,
          200.793701171875
        ]
      ],
      "group_id": null,
      "description": "118.29,188.73,151.74,212.86",
      "shape_type": "point",
      "flags": {}
    },
    {
      "label": "motorbike",
      "points": [
        [
          118.04571151733398,
          241.18313598632812
        ]
      ],
      "group_id": null,
      "description": "97.82,226.62,138.28,255.75",
      "shape_type": "point",
      "flags": {}
    },
    {
      "label": "motorbike",
      "points": [
        [
          329.73329162597656,
          187.16046905517578
        ]
      ],
      "group_id": null,
      "description": "314.01,175.81,345.46,198.51",
      "shape_type": "point",
      "flags": {}
    },
    {
      "label": "motorbike",
      "points": [
        [
          158.0477752685547,
          192.82766723632812
        ]
      ],
      "group_id": null,
      "description": "141.96,181.16,174.14,204.49",
      "shape_type": "point",
      "flags": {}
    },
    {
      "label": "motorbike",
      "points": [
        [
          255.48041534423828,
          184.1058807373047
        ]
      ],
      "group_id": null,
      "description": "240.03,173.09,270.93,195.12",
      "shape_type": "point",
      "flags": {}
    },
    {
      "label": "motorbike",
      "points": [
        [
          322.7259979248047,
          256.23107147216797
        ]
      ],
      "group_id": null,
      "description": "301.97,241.46,343.48,271.00",
      "shape_type": "point",
      "flags": {}
    },
    {
      "label": "motorbike",
      "points": [
        [
          245.6477508544922,
          161.17584991455078
        ]
      ],
      "group_id": null,
      "description": "232.28,151.43,259.01,170.92",
      "shape_type": "point",
      "flags": {}
    },
    {
      "label": "motorbike",
      "points": [
        [
          408.2016143798828,
          223.4663314819336
        ]
      ],
      "group_id": null,
      "description": "389.73,210.14,426.68,236.80",
      "shape_type": "point",
      "flags": {}
    },
    {
      "label": "motorbike",
      "points": [
        [
          140.78171920776367,
          258.77259826660156
        ]
      ],
      "group_id": null,
      "description": "120.81,244.36,160.76,273.19",
      "shape_type": "point",
      "flags": {}
    },
    {
      "label": "motorbike",
      "points": [
        [
          400.44798278808594,
          187.05702209472656
        ]
      ],
      "group_id": null,
      "description": "384.68,175.65,416.22,198.47",
      "shape_type": "point",
      "flags": {}
    },
    {
      "label": "motorbike",
      "points": [
        [
          350.4849853515625,
          175.02540588378906
        ]
      ],
      "group_id": null,
      "description": "335.71,164.42,365.26,185.63",
      "shape_type": "point",
      "flags": {}
    },
    {
      "label": "motorbike",
      "points": [
        [
          380.4894104003906,
          201.74334716796875
        ]
      ],
      "group_id": null,
      "description": "363.58,189.58,397.40,213.91",
      "shape_type": "point",
      "flags": {}
    },
    {
      "label": "motorbike",
      "points": [
        [
          340.16192626953125,
          155.6900177001953
        ]
      ],
      "group_id": null,
      "description": "326.81,145.96,353.52,165.42",
      "shape_type": "point",
      "flags": {}
    },
    {
      "label": "motorbike",
      "points": [
        [
          362.35198974609375,
          195.2823486328125
        ]
      ],
      "group_id": null,
      "description": "345.72,183.45,378.99,207.12",
      "shape_type": "point",
      "flags": {}
    },
    {
      "label": "car",
      "points": [
        [
          362.9053497314453,
          217.72836303710938
        ]
      ],
      "group_id": null,
      "description": "323.06,199.84,402.75,235.62",
      "shape_type": "point",
      "flags": {}
    },
    {
      "label": "motorbike",
      "points": [
        [
          287.3354949951172,
          147.32432556152344
        ]
      ],
      "group_id": null,
      "description": "274.84,138.18,299.83,156.47",
      "shape_type": "point",
      "flags": {}
    },
    {
      "label": "motorbike",
      "points": [
        [
          272.79908752441406,
          145.12723541259766
        ]
      ],
      "group_id": null,
      "description": "260.63,136.37,284.97,153.88",
      "shape_type": "point",
      "flags": {}
    },
    {
      "label": "motorbike",
      "points": [
        [
          153.48645782470703,
          165.02802276611328
        ]
      ],
      "group_id": null,
      "description": "139.74,154.99,167.23,175.06",
      "shape_type": "point",
      "flags": {}
    },
    {
      "label": "motorbike",
      "points": [
        [
          434.1769561767578,
          213.3341064453125
        ]
      ],
      "group_id": null,
      "description": "416.64,200.78,451.71,225.89",
      "shape_type": "point",
      "flags": {}
    },
    {
      "label": "motorbike",
      "points": [
        [
          230.52594757080078,
          112.88787841796875
        ]
      ],
      "group_id": null,
      "description": "220.70,105.64,240.35,120.14",
      "shape_type": "point",
      "flags": {}
    },
    {
      "label": "motorbike",
      "points": [
        [
          263.1840362548828,
          162.37574005126953
        ]
      ],
      "group_id": null,
      "description": "249.58,152.56,276.79,172.19",
      "shape_type": "point",
      "flags": {}
    },
    {
      "label": "motorbike",
      "points": [
        [
          275.6885070800781,
          128.60929489135742
        ]
      ],
      "group_id": null,
      "description": "264.75,120.58,286.63,136.64",
      "shape_type": "point",
      "flags": {}
    },
    {
      "label": "motorbike",
      "points": [
        [
          447.46405029296875,
          235.66876983642578
        ]
      ],
      "group_id": null,
      "description": "427.69,221.97,467.24,249.37",
      "shape_type": "point",
      "flags": {}
    },
    {
      "label": "motorbike",
      "points": [
        [
          307.53367614746094,
          117.54405212402344
        ]
      ],
      "group_id": null,
      "description": "297.44,110.07,317.62,125.02",
      "shape_type": "point",
      "flags": {}
    },
    {
      "label": "motorbike",
      "points": [
        [
          149.00955963134766,
          152.70059967041016
        ]
      ],
      "group_id": null,
      "description": "136.21,143.27,161.81,162.13",
      "shape_type": "point",
      "flags": {}
    },
    {
      "label": "motorbike",
      "points": [
        [
          165.40438842773438,
          131.91107559204102
        ]
      ],
      "group_id": null,
      "description": "154.16,123.58,176.65,140.24",
      "shape_type": "point",
      "flags": {}
    },
    {
      "label": "motorbike",
      "points": [
        [
          295.01141357421875,
          135.84235000610352
        ]
      ],
      "group_id": null,
      "description": "283.41,127.33,306.61,144.35",
      "shape_type": "point",
      "flags": {}
    },
    {
      "label": "car",
      "points": [
        [
          254.84659576416016,
          140.43118286132812
        ]
      ],
      "group_id": null,
      "description": "227.44,128.67,282.25,152.19",
      "shape_type": "point",
      "flags": {}
    },
    {
      "label": "motorbike",
      "points": [
        [
          239.58179473876953,
          132.22258377075195
        ]
      ],
      "group_id": null,
      "description": "228.12,123.92,251.04,140.53",
      "shape_type": "point",
      "flags": {}
    },
    {
      "label": "motorbike",
      "points": [
        [
          332.1592712402344,
          141.5893096923828
        ]
      ],
      "group_id": null,
      "description": "320.17,132.82,344.15,150.36",
      "shape_type": "point",
      "flags": {}
    },
    {
      "label": "motorbike",
      "points": [
        [
          283.65863037109375,
          118.68197631835938
        ]
      ],
      "group_id": null,
      "description": "273.44,111.15,293.88,126.22",
      "shape_type": "point",
      "flags": {}
    },
    {
      "label": "motorbike",
      "points": [
        [
          386.9043426513672,
          169.04197692871094
        ]
      ],
      "group_id": null,
      "description": "372.72,158.66,401.09,179.43",
      "shape_type": "point",
      "flags": {}
    },
    {
      "label": "motorbike",
      "points": [
        [
          308.8313751220703,
          183.3399200439453
        ]
      ],
      "group_id": null,
      "description": "293.42,172.34,324.24,194.34",
      "shape_type": "point",
      "flags": {}
    },
    {
      "label": "motorbike",
      "points": [
        [
          158.9965057373047,
          123.94761276245117
        ]
      ],
      "group_id": null,
      "description": "148.41,116.10,169.58,131.80",
      "shape_type": "point",
      "flags": {}
    },
    {
      "label": "car",
      "points": [
        [
          285.2526321411133,
          182.14165496826172
        ]
      ],
      "group_id": null,
      "description": "251.29,167.40,319.21,196.89",
      "shape_type": "point",
      "flags": {}
    },
    {
      "label": "motorbike",
      "points": [
        [
          160.40715789794922,
          104.72837448120117
        ]
      ],
      "group_id": null,
      "description": "151.30,97.96,169.51,111.50",
      "shape_type": "point",
      "flags": {}
    },
    {
      "label": "motorbike",
      "points": [
        [
          234.6601333618164,
          122.6562614440918
        ]
      ],
      "group_id": null,
      "description": "224.16,114.98,245.16,130.33",
      "shape_type": "point",
      "flags": {}
    },
    {
      "label": "motorbike",
      "points": [
        [
          171.35089874267578,
          120.42427444458008
        ]
      ],
      "group_id": null,
      "description": "161.03,112.75,181.67,128.10",
      "shape_type": "point",
      "flags": {}
    },
    {
      "label": "motorbike",
      "points": [
        [
          317.9985046386719,
          174.79391479492188
        ]
      ],
      "group_id": null,
      "description": "303.00,164.00,333.00,185.59",
      "shape_type": "point",
      "flags": {}
    },
    {
      "label": "motorbike",
      "points": [
        [
          251.09512329101562,
          112.25698852539062
        ]
      ],
      "group_id": null,
      "description": "241.28,104.97,260.91,119.55",
      "shape_type": "point",
      "flags": {}
    },
    {
      "label": "motorbike",
      "points": [
        [
          313.63597106933594,
          128.82771682739258
        ]
      ],
      "group_id": null,
      "description": "302.48,120.70,324.79,136.96",
      "shape_type": "point",
      "flags": {}
    },
    {
      "label": "motorbike",
      "points": [
        [
          360.68499755859375,
          153.59467315673828
        ]
      ],
      "group_id": null,
      "description": "347.44,143.92,373.93,163.27",
      "shape_type": "point",
      "flags": {}
    },
    {
      "label": "motorbike",
      "points": [
        [
          371.07000732421875,
          171.5206069946289
        ]
      ],
      "group_id": null,
      "description": "356.54,160.87,385.60,182.18",
      "shape_type": "point",
      "flags": {}
    },
    {
      "label": "motorbike",
      "points": [
        [
          326.7931823730469,
          131.63214874267578
        ]
      ],
      "group_id": null,
      "description": "315.44,123.37,338.15,139.89",
      "shape_type": "point",
      "flags": {}
    },
    {
      "label": "car",
      "points": [
        [
          319.1482849121094,
          149.3462677001953
        ]
      ],
      "group_id": null,
      "description": "290.04,136.54,348.26,162.15",
      "shape_type": "point",
      "flags": {}
    }
  ],
  "imagePath": "20251118_173002_001.jpg",
  "imageData": null,
  "imageHeight": 294,
  "imageWidth": 518
}