{
  "version": "5.10.1",
  "flags": {},
  "shapes": [
    {
      "label": "motorbike",
      "points": [
        [
          378.92333984375,
          190.53231811523438
        ]
      ],
      "group_id": null,
      "description": "362.88,179.18,394.97,201.89",
      "shape_type": "point",
      "flags": {}
    },
    {
      "label": "motorbike",
      "points": [
        [
          346.54664611816406,
          153.0085906982422
        ]
      ],
      "group_id": null,
      "description": "333.38,143.56,359.71,162.46",
      "shape_type": "point",
      "flags": {}
    },
    {
      "label": "motorbike",
      "points": [
        [
          395.9961853027344,
          160.16275024414062
        ]
      ],
      "group_id": null,
      "description": "382.37,150.32,409.62,170.01",
      "shape_type": "point",
      "flags": {}
    },
    {
      "label": "motorbike",
      "points": [
        [
          426.41062927246094,
          184.5311737060547
        ]
      ],
      "group_id": null,
      "description": "410.53,173.36,442.29,195.70",
      "shape_type": "point",
      "flags": {}
    },
    {
      "label": "motorbike",
      "points": [
        [
          405.7048645019531,
          109.86498260498047
        ]
      ],
      "group_id": null,
      "description": "396.03,102.76,415.38,116.97",
      "shape_type": "point",
      "flags": {}
    },
    {
      "label": "car",
      "points": [
        [
          207.0002212524414,
          174.80782318115234
        ]
      ],
      "group_id": null,
      "description": "173.91,160.32,240.09,189.29",
      "shape_type": "point",
      "flags": {}
    },
    {
      "label": "car",
      "points": [
        [
          322.0176696777344,
          187.21527862548828
        ]
      ],
      "group_id": null,
      "description": "286.57,171.81,357.46,202.63",
      "shape_type": "point",
      "flags": {}
    },
    {
      "label": "motorbike",
      "points": [
        [
          428.82911682128906,
          108.00204086303711
        ]
      ],
      "group_id": null,
      "description": "419.33,101.02,438.33,114.99",
      "shape_type": "point",
      "flags": {}
    },
    {
      "label": "motorbike",
      "points": [
        [
          410.6173095703125,
          168.75464630126953
        ]
      ],
      "group_id": null,
      "description": "396.09,158.38,425.14,179.13",
      "shape_type": "point",
      "flags": {}
    },
    {
      "label": "motorbike",
      "points": [
        [
          411.2752990722656,
          270.3428421020508
        ]
      ],
      "group_id": null,
      "description": "390.40,255.93,432.15,284.75",
      "shape_type": "point",
      "flags": {}
    },
    {
      "label": "motorbike",
      "points": [
        [
          295.2822723388672,
          104.02163696289062
        ]
      ],
      "group_id": null,
      "description": "286.22,97.33,304.34,110.71",
      "shape_type": "point",
      "flags": {}
    },
    {
      "label": "motorbike",
      "points": [
        [
          343.6443328857422,
          100.03593826293945
        ]
      ],
      "group_id": null,
      "description": "334.95,93.57,352.33,106.50",
      "shape_type": "point",
      "flags": {}
    },
    {
      "label": "motorbike",
      "points": [
        [
          311.6393737792969,
          98.04766082763672
        ]
      ],
      "group_id": null,
      "description": "303.03,91.64,320.25,104.45",
      "shape_type": "point",
      "flags": {}
    },
    {
      "label": "motorbike",
      "points": [
        [
          359.0724792480469,
          109.26303100585938
        ]
      ],
      "group_id": null,
      "description": "349.51,102.25,368.64,116.27",
      "shape_type": "point",
      "flags": {}
    },
    {
      "label": "motorbike",
      "points": [
        [
          324.9562225341797,
          92.1292610168457
        ]
      ],
      "group_id": null,
      "description": "316.76,86.02,333.16,98.23",
      "shape_type": "point",
      "flags": {}
    },
    {
      "label": "motorbike",
      "points": [
        [
          394.95716857910156,
          97.30079650878906
        ]
      ],
      "group_id": null,
      "description": "386.43,90.98,403.49,103.62",
      "shape_type": "point",
      "flags": {}
    }
  ],
  "imagePath": "20251117_160022_003.jpg",
  "imageData": null,
  "imageHeight": 294,
  "imageWidth": 518
}