{
  "version": "5.10.1",
  "flags": {},
  "shapes": [
    {
      "label": "motorbike",
      "points": [
        [
          275.2095489501953,
          108.8144645690918
        ]
      ],
      "group_id": null,
      "description": "265.60,101.67,284.82,115.96",
      "shape_type": "point",
      "flags": {}
    },
    {
      "label": "motorbike",
      "points": [
        [
          131.25696563720703,
          174.25037384033203
        ]
      ],
      "group_id": null,
      "description": "116.72,163.74,145.79,184.76",
      "shape_type": "point",
      "flags": {}
    },
    {
      "label": "motorbike",
      "points": [
        [
          381.95469665527344,
          125.38949203491211
        ]
      ],
      "group_id": null,
      "description": "371.18,117.43,392.72,133.35",
      "shape_type": "point",
      "flags": {}
    },
    {
      "label": "motorbike",
      "points": [
        [
          477.97650146484375,
          195.6602783203125
        ]
      ],
      "group_id": null,
      "description": "461.86,184.01,494.09,207.31",
      "shape_type": "point",
      "flags": {}
    },
    {
      "label": "car",
      "points": [
        [
          401.44334411621094,
          68.66631507873535
        ]
      ],
      "group_id": null,
      "description": "384.10,61.36,418.79,75.97",
      "shape_type": "point",
      "flags": {}
    },
    {
      "label": "motorbike",
      "points": [
        [
          435.1306457519531,
          86.37809753417969
        ]
      ],
      "group_id": null,
      "description": "427.18,80.50,443.08,92.26",
      "shape_type": "point",
      "flags": {}
    },
    {
      "label": "car",
      "points": [
        [
          321.1883239746094,
          91.00992584228516
        ]
      ],
      "group_id": null,
      "description": "302.76,83.27,339.62,98.75",
      "shape_type": "point",
      "flags": {}
    },
    {
      "label": "car",
      "points": [
        [
          57.8413143157959,
          209.0817108154297
        ]
      ],
      "group_id": null,
      "description": "16.47,191.81,99.21,226.36",
      "shape_type": "point",
      "flags": {}
    },
    {
      "label": "motorbike",
      "points": [
        [
          385.71575927734375,
          64.9833755493164
        ]
      ],
      "group_id": null,
      "description": "378.21,59.39,393.22,70.57",
      "shape_type": "point",
      "flags": {}
    },
    {
      "label": "motorbike",
      "points": [
        [
          354.7278289794922,
          75.24386596679688
        ]
      ],
      "group_id": null,
      "description": "347.17,69.59,362.29,80.90",
      "shape_type": "point",
      "flags": {}
    },
    {
      "label": "motorbike",
      "points": [
        [
          362.9699401855469,
          262.58052825927734
        ]
      ],
      "group_id": null,
      "description": "341.71,247.50,384.23,277.67",
      "shape_type": "point",
      "flags": {}
    },
    {
      "label": "motorbike",
      "points": [
        [
          344.6381072998047,
          72.57475662231445
        ]
      ],
      "group_id": null,
      "description": "337.27,66.86,352.00,78.29",
      "shape_type": "point",
      "flags": {}
    },
    {
      "label": "motorbike",
      "points": [
        [
          152.12346649169922,
          125.41706085205078
        ]
      ],
      "group_id": null,
      "description": "141.47,117.56,162.78,133.27",
      "shape_type": "point",
      "flags": {}
    },
    {
      "label": "motorbike",
      "points": [
        [
          20.96955442428589,
          160.9709243774414
        ]
      ],
      "group_id": null,
      "description": "7.50,151.30,34.44,170.64",
      "shape_type": "point",
      "flags": {}
    },
    {
      "label": "motorbike",
      "points": [
        [
          482.0701904296875,
          49.5301399230957
        ]
      ],
      "group_id": null,
      "description": "474.32,43.86,489.82,55.20",
      "shape_type": "point",
      "flags": {}
    },
    {
      "label": "car",
      "points": [
        [
          217.78914642333984,
          127.37838745117188
        ]
      ],
      "group_id": null,
      "description": "193.57,116.94,242.01,137.81",
      "shape_type": "point",
      "flags": {}
    },
    {
      "label": "car",
      "points": [
        [
          487.34796142578125,
          34.79858589172363
        ]
      ],
      "group_id": null,
      "description": "469.76,27.70,504.93,41.89",
      "shape_type": "point",
      "flags": {}
    },
    {
      "label": "motorbike",
      "points": [
        [
          284.47825622558594,
          91.01546859741211
        ]
      ],
      "group_id": null,
      "description": "276.40,85.01,292.55,97.03",
      "shape_type": "point",
      "flags": {}
    },
    {
      "label": "car",
      "points": [
        [
          459.2122497558594,
          59.647300720214844
        ]
      ],
      "group_id": null,
      "description": "441.45,52.31,476.98,66.99",
      "shape_type": "point",
      "flags": {}
    },
    {
      "label": "motorbike",
      "points": [
        [
          386.8294219970703,
          89.84012985229492
        ]
      ],
      "group_id": null,
      "description": "378.85,83.90,394.81,95.78",
      "shape_type": "point",
      "flags": {}
    },
    {
      "label": "car",
      "points": [
        [
          364.4832458496094,
          102.80073547363281
        ]
      ],
      "group_id": null,
      "description": "344.11,94.15,384.85,111.45",
      "shape_type": "point",
      "flags": {}
    },
    {
      "label": "motorbike",
      "points": [
        [
          374.6012878417969,
          82.6588020324707
        ]
      ],
      "group_id": null,
      "description": "366.84,76.94,382.36,88.38",
      "shape_type": "point",
      "flags": {}
    },
    {
      "label": "motorbike",
      "points": [
        [
          443.97760009765625,
          55.22233772277832
        ]
      ],
      "group_id": null,
      "description": "436.32,49.56,451.64,60.89",
      "shape_type": "point",
      "flags": {}
    },
    {
      "label": "car",
      "points": [
        [
          497.5099639892578,
          41.03734588623047
        ]
      ],
      "group_id": null,
      "description": "479.79,33.73,515.23,48.34",
      "shape_type": "point",
      "flags": {}
    },
    {
      "label": "car",
      "points": [
        [
          501.95074462890625,
          47.614715576171875
        ]
      ],
      "group_id": null,
      "description": "486.95,40.46,516.95,54.77",
      "shape_type": "point",
      "flags": {}
    },
    {
      "label": "motorbike",
      "points": [
        [
          465.54115295410156,
          42.10746955871582
        ]
      ],
      "group_id": null,
      "description": "457.93,36.54,473.15,47.68",
      "shape_type": "point",
      "flags": {}
    }
  ],
  "imagePath": "20251117_160745_047.jpg",
  "imageData": null,
  "imageHeight": 294,
  "imageWidth": 518
}