{
  "version": "5.10.1",
  "flags": {},
  "shapes": [
    {
      "label": "motorbike",
      "points": [
        [
          223.53397369384766,
          153.82984161376953
        ]
      ],
      "group_id": null,
      "description": "210.17,144.11,236.90,163.55",
      "shape_type": "point",
      "flags": {}
    },
    {
      "label": "motorbike",
      "points": [
        [
          235.75841522216797,
          105.21096420288086
        ]
      ],
      "group_id": null,
      "description": "226.54,98.35,244.97,112.07",
      "shape_type": "point",
      "flags": {}
    },
    {
      "label": "motorbike",
      "points": [
        [
          203.0458755493164,
          155.5066680908203
        ]
      ],
      "group_id": null,
      "description": "189.70,145.84,216.39,165.17",
      "shape_type": "point",
      "flags": {}
    },
    {
      "label": "motorbike",
      "points": [
        [
          254.74952697753906,
          141.7792739868164
        ]
      ],
      "group_id": null,
      "description": "242.47,132.89,267.03,150.67",
      "shape_type": "point",
      "flags": {}
    },
    {
      "label": "motorbike",
      "points": [
        [
          255.14617919921875,
          95.93116760253906
        ]
      ],
      "group_id": null,
      "description": "246.62,89.48,263.68,102.39",
      "shape_type": "point",
      "flags": {}
    },
    {
      "label": "motorbike",
      "points": [
        [
          275.41941833496094,
          97.07943725585938
        ]
      ],
      "group_id": null,
      "description": "266.88,90.62,283.96,103.54",
      "shape_type": "point",
      "flags": {}
    },
    {
      "label": "motorbike",
      "points": [
        [
          178.10845947265625,
          275.6947326660156
        ]
      ],
      "group_id": null,
      "description": "156.66,260.94,199.56,290.45",
      "shape_type": "point",
      "flags": {}
    },
    {
      "label": "car",
      "points": [
        [
          315.4459991455078,
          127.48440170288086
        ]
      ],
      "group_id": null,
      "description": "289.85,116.06,341.04,138.90",
      "shape_type": "point",
      "flags": {}
    }
  ],
  "imagePath": "20251118_170703_042.jpg",
  "imageData": null,
  "imageHeight": 294,
  "imageWidth": 518
}