{
  "version": "6.2.0",
  "flags": {},
  "shapes": [
    {
      "label": "car",
      "points": [
        [
          151.56676483154297,
          251.5189666748047
        ]
      ],
      "group_id": null,
      "description": "105.04,230.56,198.09,272.48",
      "shape_type": "point",
      "flags": {},
      "mask": null
    },
    {
      "label": "car",
      "points": [
        [
          259.6899948120117,
          134.79939651489258
        ]
      ],
      "group_id": null,
      "description": "233.08,123.12,286.30,146.47",
      "shape_type": "point",
      "flags": {},
      "mask": null
    },
    {
      "label": "motorbike",
      "points": [
        [
          355.2218322753906,
          138.4421844482422
        ]
      ],
      "group_id": null,
      "description": "343.19,129.63,367.26,147.25",
      "shape_type": "point",
      "flags": {},
      "mask": null
    },
    {
      "label": "coach",
      "points": [
        [
          296.2852233676976,
          181.3642611683849
        ]
      ],
      "group_id": null,
      "description": "",
      "shape_type": "point",
      "flags": {},
      "mask": null
    },
    {
      "label": "coach",
      "points": [
        [
          311.7491408934708,
          87.20618556701032
        ]
      ],
      "group_id": null,
      "description": "",
      "shape_type": "point",
      "flags": {},
      "mask": null
    },
    {
      "label": "motorbike",
      "points": [
        [
          374.6357388316151,
          169.3367697594502
        ]
      ],
      "group_id": null,
      "description": "",
      "shape_type": "point",
      "flags": {},
      "mask": null
    },
    {
      "label": "motorbike",
      "points": [
        [
          203.15807560137458,
          93.04810996563575
        ]
      ],
      "group_id": null,
      "description": "",
      "shape_type": "point",
      "flags": {},
      "mask": null
    }
  ],
  "imagePath": "20251116_143813_047.jpg",
  "imageData": null,
  "imageHeight": 294,
  "imageWidth": 518
}