{
  "version": "6.3.0",
  "flags": {},
  "shapes": [
    {
      "label": "car",
      "points": [
        [
          273.761962890625,
          256.16658782958984
        ]
      ],
      "group_id": null,
      "description": "228.88,236.48,318.64,275.85",
      "shape_type": "point",
      "flags": {},
      "mask": null
    },
    {
      "label": "motorbike",
      "points": [
        [
          250.3275604248047,
          122.68324661254883
        ]
      ],
      "group_id": null,
      "description": "239.80,114.99,260.85,130.38",
      "shape_type": "point",
      "flags": {},
      "mask": null
    },
    {
      "label": "car",
      "points": [
        [
          202.15480041503906,
          108.89916229248047
        ]
      ],
      "group_id": null,
      "description": "180.44,99.79,223.87,118.00",
      "shape_type": "point",
      "flags": {},
      "mask": null
    },
    {
      "label": "motorbike",
      "points": [
        [
          414.3423767089844,
          156.72889709472656
        ]
      ],
      "group_id": null,
      "description": "401.31,147.22,427.37,166.24",
      "shape_type": "point",
      "flags": {},
      "mask": null
    },
    {
      "label": "car",
      "points": [
        [
          165.25733184814453,
          103.34579849243164
        ]
      ],
      "group_id": null,
      "description": "144.78,94.66,185.74,112.03",
      "shape_type": "point",
      "flags": {},
      "mask": null
    },
    {
      "label": "motorbike",
      "points": [
        [
          347.60679626464844,
          186.6887435913086
        ]
      ],
      "group_id": null,
      "description": "331.81,175.39,363.41,197.98",
      "shape_type": "point",
      "flags": {},
      "mask": null
    },
    {
      "label": "motorbike",
      "points": [
        [
          221.6907501220703,
          122.26106643676758
        ]
      ],
      "group_id": null,
      "description": "211.02,114.46,232.36,130.06",
      "shape_type": "point",
      "flags": {},
      "mask": null
    },
    {
      "label": "motorbike",
      "points": [
        [
          236.05664825439453,
          116.19197463989258
        ]
      ],
      "group_id": null,
      "description": "226.06,108.83,246.06,123.55",
      "shape_type": "point",
      "flags": {},
      "mask": null
    },
    {
      "label": "motorbike",
      "points": [
        [
          204.38396453857422,
          165.3357696533203
        ]
      ],
      "group_id": null,
      "description": "190.04,155.05,218.72,175.62",
      "shape_type": "point",
      "flags": {},
      "mask": null
    },
    {
      "label": "motorbike",
      "points": [
        [
          243.62612915039062,
          116.52170181274414
        ]
      ],
      "group_id": null,
      "description": "233.67,109.14,253.58,123.90",
      "shape_type": "point",
      "flags": {},
      "mask": null
    },
    {
      "label": "car",
      "points": [
        [
          107.81885147094727,
          155.80062103271484
        ]
      ],
      "group_id": null,
      "description": "77.51,142.80,138.13,168.81",
      "shape_type": "point",
      "flags": {},
      "mask": null
    },
    {
      "label": "motorbike",
      "points": [
        [
          254.15311431884766,
          111.13846206665039
        ]
      ],
      "group_id": null,
      "description": "244.68,104.07,263.63,118.21",
      "shape_type": "point",
      "flags": {},
      "mask": null
    },
    {
      "label": "motorbike",
      "points": [
        [
          433.7422680412371,
          198.54639175257734
        ]
      ],
      "group_id": null,
      "description": "",
      "shape_type": "point",
      "flags": {},
      "mask": null
    }
  ],
  "imagePath": "20251116_144720_099.jpg",
  "imageData": null,
  "imageHeight": 294,
  "imageWidth": 518
}