{
  "version": "5.10.1",
  "flags": {},
  "shapes": [
    {
      "label": "car",
      "points": [
        [
          394.84300231933594,
          220.5176544189453
        ]
      ],
      "group_id": null,
      "description": "352.76,202.25,436.92,238.79",
      "shape_type": "point",
      "flags": {}
    },
    {
      "label": "motorbike",
      "points": [
        [
          298.2633056640625,
          174.86297607421875
        ]
      ],
      "group_id": null,
      "description": "283.14,164.02,313.38,185.71",
      "shape_type": "point",
      "flags": {}
    },
    {
      "label": "motorbike",
      "points": [
        [
          341.2039031982422,
          173.11962127685547
        ]
      ],
      "group_id": null,
      "description": "326.02,162.12,356.39,184.12",
      "shape_type": "point",
      "flags": {}
    },
    {
      "label": "motorbike",
      "points": [
        [
          100.87698364257812,
          218.22333526611328
        ]
      ],
      "group_id": null,
      "description": "82.07,204.77,119.69,231.67",
      "shape_type": "point",
      "flags": {}
    },
    {
      "label": "car",
      "points": [
        [
          260.03826904296875,
          110.94491958618164
        ]
      ],
      "group_id": null,
      "description": "237.23,101.39,282.85,120.50",
      "shape_type": "point",
      "flags": {}
    },
    {
      "label": "motorbike",
      "points": [
        [
          269.35462188720703,
          245.8019027709961
        ]
      ],
      "group_id": null,
      "description": "247.70,230.46,291.01,261.15",
      "shape_type": "point",
      "flags": {}
    },
    {
      "label": "motorbike",
      "points": [
        [
          180.30789947509766,
          135.38381576538086
        ]
      ],
      "group_id": null,
      "description": "168.38,126.77,192.24,144.00",
      "shape_type": "point",
      "flags": {}
    },
    {
      "label": "car",
      "points": [
        [
          200.25991821289062,
          148.13450622558594
        ]
      ],
      "group_id": null,
      "description": "171.47,135.66,229.05,160.61",
      "shape_type": "point",
      "flags": {}
    },
    {
      "label": "motorbike",
      "points": [
        [
          359.4775695800781,
          148.33900451660156
        ]
      ],
      "group_id": null,
      "description": "346.21,138.81,372.74,157.87",
      "shape_type": "point",
      "flags": {}
    },
    {
      "label": "motorbike",
      "points": [
        [
          289.71800231933594,
          206.12396240234375
        ]
      ],
      "group_id": null,
      "description": "272.09,193.48,307.35,218.77",
      "shape_type": "point",
      "flags": {}
    }
  ],
  "imagePath": "20251118_173522_033.jpg",
  "imageData": null,
  "imageHeight": 294,
  "imageWidth": 518
}