{
  "version": "6.3.0",
  "flags": {},
  "shapes": [
    {
      "label": "car",
      "points": [
        [
          292.0533752441406,
          114.09355926513672
        ]
      ],
      "group_id": null,
      "description": "270.40,104.67,313.71,123.52",
      "shape_type": "point",
      "flags": {},
      "mask": null
    },
    {
      "label": "car",
      "points": [
        [
          149.8239700374532,
          109.17228464419478
        ]
      ],
      "group_id": null,
      "description": "",
      "shape_type": "point",
      "flags": {},
      "mask": null
    }
  ],
  "imagePath": "20251116_140027_003.jpg",
  "imageData": null,
  "imageHeight": 294,
  "imageWidth": 518
}